irctk/__init__.py
irctk/channel.py
irctk/client.py
irctk/command.py
irctk/isupport.py
irctk/message.py
irctk/nick.py
irctk/numerics.py
irc_toolkit-0.4.0.dist-info/LICENSE
irc_toolkit-0.4.0.dist-info/METADATA
irc_toolkit-0.4.0.dist-info/WHEEL
irc_toolkit-0.4.0.dist-info/RECORD
