Metadata-Version: 2.1
Name: irc-toolkit
Version: 0.4.0
Summary: A Python IRCv3 Client Library
License: BSD
Author: Kyle Fuller
Author-email: kyle@fuller.li
Requires-Python: >=3.9,<4.0
Classifier: License :: Other/Proprietary License
Classifier: Programming Language :: Python :: 3
Classifier: Programming Language :: Python :: 3.9
Classifier: Programming Language :: Python :: 3.10
Classifier: Programming Language :: Python :: 3.11
Classifier: Programming Language :: Python :: 3.12
